marshmallow_i18n_messages/__init__.py
marshmallow_i18n_messages/extract_translations.py
marshmallow_i18n_messages/marshmallow_iterator.py
marshmallow_i18n_messages/patch_marshmallow.py
marshmallow_i18n_messages-0.1.1.dist-info/licenses/LICENSE
marshmallow_i18n_messages-0.1.1.dist-info/METADATA
marshmallow_i18n_messages-0.1.1.dist-info/WHEEL
marshmallow_i18n_messages-0.1.1.dist-info/entry_points.txt
marshmallow_i18n_messages-0.1.1.dist-info/top_level.txt
marshmallow_i18n_messages-0.1.1.dist-info/RECORD
