Metadata-Version: 2.4
Name: marshmallow-i18n-messages
Version: 0.1.1
Summary: A patch to marshmallow to allow to translate marshmallow messages via GNU gettext
Home-page: https://github.com/oarepo/marshmallow-i18n-messages
Author: Miroslav Simek
Author-email: miroslav.simek@cesnet.cz
Project-URL: Bug Tracker, https://github.com/oarepo/marshmallow-i18n-messages/issues
Classifier: Programming Language :: Python :: 3
Classifier: License :: OSI Approved :: MIT License
Classifier: Operating System :: OS Independent
Requires-Python: >=3.10
License-File: LICENSE
Requires-Dist: marshmallow
Requires-Dist: marshmallow-utils
Requires-Dist: babel
Requires-Dist: speaklater
Provides-Extra: tests
Requires-Dist: pytest; extra == "tests"
Provides-Extra: dev
Requires-Dist: polib; extra == "dev"
Dynamic: license-file
